mlflow_polylog/__init__.py
mlflow_polylog/_internal.py
mlflow_polylog/defaults.py
mlflow_polylog/functions.py
mlflow_polylog/log.py
mlflow_polylog/type_mapping.py
mlflow_polylog-0.0.1.dist-info/METADATA
mlflow_polylog-0.0.1.dist-info/WHEEL
mlflow_polylog-0.0.1.dist-info/top_level.txt
mlflow_polylog-0.0.1.dist-info/RECORD
