Metadata-Version: 2.4
Name: mlflow_polylog
Version: 0.0.1
Summary: A polymorphic model logging utility for MLflow that enables seamless logging of machine learning models from various libraries without requiring explicit type specification or installation of all supported frameworks. It dynamically detects installed libraries and maps model types to the appropriate MLflow logging functions.
Author-email: Barkov Mikhail <mik.bar@tutamail.com>
Requires-Python: >=3.10
Requires-Dist: mlflow>=2.13.0
Requires-Dist: importlib-metadata; python_version >= "3.10"
Provides-Extra: tests
Requires-Dist: pytest==8.3.4; extra == "tests"
Requires-Dist: pytest-lazy-fixtures==1.1.2; extra == "tests"
Requires-Dist: catboost; extra == "tests"
Requires-Dist: lightgbm; extra == "tests"
Requires-Dist: xgboost; extra == "tests"
Requires-Dist: scikit-learn; extra == "tests"
Provides-Extra: lint
Requires-Dist: ruff==0.11.13; extra == "lint"
Requires-Dist: flake8==7.2.0; extra == "lint"
Requires-Dist: wemake-python-styleguide==1.1.0; extra == "lint"
Requires-Dist: flake8-pyproject==1.2.3; extra == "lint"
Provides-Extra: typing
Requires-Dist: mypy==1.15.0; extra == "typing"
